odoo/addons/delivery_carrier_return_barcode_pattern/README.rst
odoo/addons/delivery_carrier_return_barcode_pattern/__init__.py
odoo/addons/delivery_carrier_return_barcode_pattern/__manifest__.py
odoo/addons/delivery_carrier_return_barcode_pattern/i18n/delivery_carrier_return_barcode_pattern.pot
odoo/addons/delivery_carrier_return_barcode_pattern/i18n/es.po
odoo/addons/delivery_carrier_return_barcode_pattern/models/__init__.py
odoo/addons/delivery_carrier_return_barcode_pattern/models/delivery_carrier.py
odoo/addons/delivery_carrier_return_barcode_pattern/readme/CONTRIBUTORS.rst
odoo/addons/delivery_carrier_return_barcode_pattern/readme/DESCRIPTION.rst
odoo/addons/delivery_carrier_return_barcode_pattern/static/description/icon.png
odoo/addons/delivery_carrier_return_barcode_pattern/static/description/index.html
odoo/addons/delivery_carrier_return_barcode_pattern/tests/__init__.py
odoo/addons/delivery_carrier_return_barcode_pattern/tests/test_delivery_carrier_return_barcode.py
odoo/addons/delivery_carrier_return_barcode_pattern/views/delivery_carrier.xml
odoo14_addon_delivery_carrier_return_barcode_pattern-14.0.1.0.1.dist-info/METADATA
odoo14_addon_delivery_carrier_return_barcode_pattern-14.0.1.0.1.dist-info/WHEEL
odoo14_addon_delivery_carrier_return_barcode_pattern-14.0.1.0.1.dist-info/top_level.txt
odoo14_addon_delivery_carrier_return_barcode_pattern-14.0.1.0.1.dist-info/RECORD
